pokitdok/__init__.py
pokitdok/api/__init__.py
pokitdok/api/client.py
pokitdok-2.8.1.dist-info/DESCRIPTION.rst
pokitdok-2.8.1.dist-info/METADATA
pokitdok-2.8.1.dist-info/RECORD
pokitdok-2.8.1.dist-info/WHEEL
pokitdok-2.8.1.dist-info/metadata.json
pokitdok-2.8.1.dist-info/top_level.txt
tests/__init__.py
tests/test_api_client.py
