Metadata-Version: 2.0
Name: pokitdok
Version: 2.8.1
Summary: PokitDok Platform API Client
Home-page: https://platform.pokitdok.com
Author: PokitDok, Inc.
Author-email: platform@pokitdok.com
License: MIT
Download-URL: https://github.com/pokitdok/pokitdok-python/tarball/2.8.1
Keywords: health,api,pokitdok,X12,eligibility,claims,providers,prices,healthcare,referrals,authorizations,insurance,plans,benefits,enrollment
Platform: any
Classifier: Development Status :: 5 - Production/Stable
Classifier: Environment :: Web Environment
Classifier: Intended Audience :: Developers
Classifier: Intended Audience :: Healthcare Industry
Classifier: License :: OSI Approved :: MIT License
Classifier: Operating System :: OS Independent
Classifier: Programming Language :: Python
Classifier: Programming Language :: Python :: 2.6
Classifier: Programming Language :: Python :: 2.7
Classifier: Programming Language :: Python :: 3.6
Classifier: Programming Language :: Python :: 3.7
Classifier: Programming Language :: Python :: Implementation :: PyPy
Classifier: Topic :: Internet :: WWW/HTTP :: Dynamic Content
Classifier: Topic :: Software Development :: Libraries :: Python Modules
Requires-Dist: requests (>=2.21.0)
Requires-Dist: oauthlib (==2.1.0)
Requires-Dist: requests-oauthlib (==1.0.0)
